questions_pkg/__init__.py
questions_pkg/questions.py
questions_pkg_joanclopezm-0.0.1.dist-info/LICENCE
questions_pkg_joanclopezm-0.0.1.dist-info/METADATA
questions_pkg_joanclopezm-0.0.1.dist-info/WHEEL
questions_pkg_joanclopezm-0.0.1.dist-info/top_level.txt
questions_pkg_joanclopezm-0.0.1.dist-info/RECORD
