Metadata-Version: 2.1
Name: questions-pkg-joanclopezm
Version: 0.0.1
Summary: Depression test to calculate depression
Home-page: https://github.com/x20232535/depress_test
Author: joan lopez
Author-email: joanclopezm@gmail.com
License: UNKNOWN
Platform: UNKNOWN
Classifier: Programming Language :: Python :: 3
Classifier: License :: OSI Approved :: MIT License
Classifier: Operating System :: OS Independent
Requires-Python: >=3.6
License-File: LICENCE
